{
  "profiles": [
    {
      "id": "grunt_easy",
      "label": "Новобранец",
      "difficulty": "easy",
      "reactionTime": 0.75,
      "aimAccuracy": 0.3,
      "visionRange": 18,
      "hearingSensitivity": 0.4,
      "decisionStyle": "reactive",
      "combatStyle": "melee",
      "preferredTactics": ["group_chase", "basic_flank"],
      "morale": 0.2,
      "fallbackThreshold": 0.8,
      "aggression": 0.4,
      "retreatStyle": "panic",
      "memoryRetention": 1500
    },
    {
      "id": "soldier_standard",
      "label": "Пехотинец",
      "difficulty": "medium",
      "reactionTime": 0.5,
      "aimAccuracy": 0.5,
      "visionRange": 25,
      "hearingSensitivity": 0.7,
      "decisionStyle": "semi_predictive",
      "combatStyle": "balanced",
      "preferredTactics": ["cover_seek", "crossfire", "ambush"],
      "morale": 0.5,
      "fallbackThreshold": 0.6,
      "aggression": 0.6,
      "retreatStyle": "strategic",
      "memoryRetention": 4000
    },
    {
      "id": "commander_elite",
      "label": "Командир",
      "difficulty": "hard",
      "reactionTime": 0.25,
      "aimAccuracy": 0.85,
      "visionRange": 35,
      "hearingSensitivity": 0.9,
      "decisionStyle": "anticipatory",
      "combatStyle": "ranged",
      "preferredTactics": ["advanced_flank", "decoy", "pin_and_push", "drone_support"],
      "morale": 0.9,
      "fallbackThreshold": 0.3,
      "aggression": 0.9,
      "retreatStyle": "tactical_regroup",
      "memoryRetention": 8000
    },
    {
      "id": "infiltrator_shadow",
      "label": "Тень",
      "difficulty": "extreme",
      "reactionTime": 0.15,
      "aimAccuracy": 0.7,
      "visionRange": 40,
      "hearingSensitivity": 1.0,
      "decisionStyle": "stealth_predictive",
      "combatStyle": "melee_stealth",
      "preferredTactics": ["invisibility", "silent_kill", "decoy_lure", "multi_path"],
      "morale": 0.95,
      "fallbackThreshold": 0.2,
      "aggression": 0.8,
      "retreatStyle": "vanish",
      "memoryRetention": 10000
    }
  ],
  "version": "1.0.0",
  "meta": {
    "description": "AI профили противников TeslaAI Genesis. Используются для адаптивного поведения, сложности и стилей боя.",
    "lastUpdated": "2025-07-30T10:00:00Z",
    "maintainer": "AI Behavior Core Consortium"
  }
}
